README.md
setup.py
commonlib/__init__.py
commonlib/confighttp.py
commonlib/connectdb.py
commonlib/htmlresult.py
commonlib/sendemail.py
lyhapi_autotest.egg-info/PKG-INFO
lyhapi_autotest.egg-info/SOURCES.txt
lyhapi_autotest.egg-info/dependency_links.txt
lyhapi_autotest.egg-info/top_level.txt