Metadata-Version: 2.1
Name: lyhapi-autotest
Version: 0.0.16
Summary: lyh interface autoTest
Home-page: https://github.com/vissyzhu/lyhapi.git
Author: vissy0429
Author-email: 1187463903@qq.com
License: MIT
Platform: UNKNOWN
